{
  "name": "Devocional Diário - Exemplo n8n",
  "nodes": [
    {
      "parameters": {
        "rule": {
          "interval": [
            {
              "field": "cronExpression",
              "value": "0 8 * * *"
            }
          ]
        }
      },
      "name": "Trigger Diário 8h",
      "type": "n8n-nodes-base.scheduleTrigger",
      "typeVersion": 1,
      "position": [
        240,
        300
      ]
    },
    {
      "parameters": {
        "url": "https://seu-usuario.github.io/devocional-diario/api.html?endpoint=today",
        "options": {}
      },
      "name": "Buscar Devocional",
      "type": "n8n-nodes-base.httpRequest",
      "typeVersion": 1,
      "position": [
        460,
        300
      ]
    },
    {
      "parameters": {
        "values": {
          "string": [
            {
              "name": "titulo",
              "value": "={{$json[\"data\"][\"titulo\"]}}"
            },
            {
              "name": "versiculo",
              "value": "={{$json[\"data\"][\"versiculo\"]}}"
            },
            {
              "name": "referencia",
              "value": "={{$json[\"data\"][\"referencia\"]}}"
            },
            {
              "name": "reflexao",
              "value": "={{$json[\"data\"][\"reflexao\"]}}"
            },
            {
              "name": "oracao",
              "value": "={{$json[\"data\"][\"oracao\"]}}"
            }
          ]
        },
        "options": {}
      },
      "name": "Processar Dados",
      "type": "n8n-nodes-base.set",
      "typeVersion": 1,
      "position": [
        680,
        300
      ]
    },
    {
      "parameters": {
        "subject": "🙏 Devocional do Dia - {{$json[\"titulo\"]}}",
        "message": "=**{{$json[\"titulo\"]}}**\n\n📖 **Versículo:**\n*\"{{$json[\"versiculo\"]}}\"*\n**{{$json[\"referencia\"]}}**\n\n💭 **Reflexão:**\n{{$json[\"reflexao\"]}}\n\n🙏 **Oração:**\n{{$json[\"oracao\"]}}\n\n---\nDevocional enviado automaticamente via n8n",
        "options": {}
      },
      "name": "Enviar Email",
      "type": "n8n-nodes-base.emailSend",
      "typeVersion": 1,
      "position": [
        900,
        300
      ]
    }
  ],
  "connections": {
    "Trigger Diário 8h": {
      "main": [
        [
          {
            "node": "Buscar Devocional",
            "type": "main",
            "index": 0
          }
        ]
      ]
    },
    "Buscar Devocional": {
      "main": [
        [
          {
            "node": "Processar Dados",
            "type": "main",
            "index": 0
          }
        ]
      ]
    },
    "Processar Dados": {
      "main": [
        [
          {
            "node": "Enviar Email",
            "type": "main",
            "index": 0
          }
        ]
      ]
    }
  }
}

